expressionizer/__init__.py
expressionizer/equation_generation.py
expressionizer/evaluator.py
expressionizer/expression.py
expressionizer/procedural.py
expressionizer/render.py
expressionizer/solve_equation.py
expressionizer/test.py
expressionizer-0.7.5.dist-info/METADATA
expressionizer-0.7.5.dist-info/WHEEL
expressionizer-0.7.5.dist-info/top_level.txt
expressionizer-0.7.5.dist-info/RECORD
