Metadata-Version: 2.4
Name: expressionizer
Version: 0.7.5
Summary: A Python library for symbolic math expressions and evaluation.
Author-email: Hudson Gouge <hudson.gouge@icloud.com>
License: MIT
Project-URL: Homepage, https://pypi.org/project/expressionizer/
Classifier: Programming Language :: Python :: 3
Classifier: License :: OSI Approved :: MIT License
Classifier: Operating System :: OS Independent
Requires-Python: >=3.8
